sonos_moments/__init__.py
sonos_moments/app.py
sonos_moments/model/__init__.py
sonos_moments/model/device.py
sonos_moments/model/group.py
sonos_moments/model/moment.py
sonos_moments/model/system.py
sonos_moments/ui/__init__.py
sonos_moments/ui/moments.py
sonos_moments/ui/speakers.py
sonos_moments/version.py
sonos_moments-0.2.0.dist-info/LICENSE
sonos_moments-0.2.0.dist-info/METADATA
sonos_moments-0.2.0.dist-info/WHEEL
sonos_moments-0.2.0.dist-info/entry_points.txt
sonos_moments-0.2.0.dist-info/RECORD
