Metadata-Version: 2.1
Name: sonos-moments
Version: 0.2.0
Summary: Sonos Controller based on NiceGUI
License: MIT
Author: Falko Schindler
Author-email: mail@falkoschindler.de
Requires-Python: >=3.11,<4.0
Classifier: License :: OSI Approved :: MIT License
Classifier: Programming Language :: Python :: 3
Classifier: Programming Language :: Python :: 3.11
Classifier: Programming Language :: Python :: 3.12
Requires-Dist: dataclasses-json (>=0.6.7,<0.7.0)
Requires-Dist: nicegui (>=2.7.0,<3.0.0)
Requires-Dist: soco (>=0.30.4,<0.31.0)
